cnextlib/.env
cnextlib/.gitignore
cnextlib/README.md
cnextlib/__init__.py
cnextlib/dataframe.py
cnextlib/df_status_hook.py
cnextlib/df_updates.py
cnextlib/libs/__init__.py
cnextlib/libs/json_serializable.py
cnextlib/mime_types.py
cnextlib/tests/.ipynb_checkpoints/Test-checkpoint.ipynb
cnextlib/tests/Test.ipynb
cnextlib/tests/__init__.py
cnextlib/tests/data/housing_data/data.csv
cnextlib/tests/data/housing_data/small-data.csv
cnextlib/tests/data/housing_data/train.csv
cnextlib/tests/data/machine-simulation/21549286_out.csv
cnextlib/tests/sample.py
cnextlib/tests/test_loc_func.py
cnextlib/tests/test_status_hook.py
cnextlib/udf_manager.py
cnextlib/user_space.py
cnextlib/utils.py
cnextlib-0.7.2.dist-info/WHEEL
cnextlib-0.7.2.dist-info/METADATA
cnextlib-0.7.2.dist-info/RECORD
